jutge/toolkit/code_metrics.py
jutge/toolkit/commented_code_detector.py
jutge/toolkit/compilers.py
jutge/toolkit/problems.py
jutge/toolkit/quizzes.py
jutge/toolkit/sanitize.py
jutge/toolkit/start.py
jutge/toolkit/sty/html.sty
jutge/toolkit/sty/jutge.sty
jutge/toolkit/sty/lang.ca.sty
jutge/toolkit/sty/lang.de.sty
jutge/toolkit/sty/lang.en.sty
jutge/toolkit/sty/lang.es.sty
jutge/toolkit/sty/lang.fr.sty
jutge/toolkit/sty/picins.sty
jutge_toolkit-3.0.1.dist-info/LICENSE.txt
jutge_toolkit-3.0.1.dist-info/METADATA
jutge_toolkit-3.0.1.dist-info/WHEEL
jutge_toolkit-3.0.1.dist-info/entry_points.txt
jutge_toolkit-3.0.1.dist-info/top_level.txt
jutge_toolkit-3.0.1.dist-info/RECORD
