Metadata-Version: 2.1
Name: jutge-toolkit
Version: 3.0.1
Summary: Toolkit to make problems for Jutge.org
Home-page: https://github.com/jutge-org/jutge-toolkit
Download-URL: https://github.com/jutge-org/jutge-toolkit/tarball/3.0.1
Author: Jordi Petit et al
Author-email: jpetit@cs.upc.edu
License: Apache
Keywords: jutge,jutge.org,education,problems,quizzes,toolkit
License-File: LICENSE.txt
Requires-Dist: jutge-util
Requires-Dist: pyyaml >=5.1
Requires-Dist: colorama
Requires-Dist: lizard
Requires-Dist: turtle-pil
Requires-Dist: easyinput
Requires-Dist: yogi
Requires-Dist: pytokr
Requires-Dist: beautifulsoup4
Requires-Dist: biopython
Requires-Dist: matplotlib
Requires-Dist: more-itertools
Requires-Dist: networkx
Requires-Dist: numpy
Requires-Dist: pandas
Requires-Dist: scipy
Requires-Dist: simpy
